stitchlab_agentcore/__init__.py
stitchlab_agentcore/config.py
stitchlab_agentcore/py.typed
stitchlab_agentcore/schema.py
stitchlab_agentcore/utils.py
stitchlab_agentcore/runtime/__init__.py
stitchlab_agentcore/runtime/app.py
stitchlab_agentcore/runtime/factory.py
stitchlab_agentcore-0.1.4.dist-info/licenses/LICENSE
stitchlab_agentcore-0.1.4.dist-info/METADATA
stitchlab_agentcore-0.1.4.dist-info/WHEEL
stitchlab_agentcore-0.1.4.dist-info/top_level.txt
stitchlab_agentcore-0.1.4.dist-info/RECORD
