Metadata-Version: 2.4
Name: stitchlab-agentcore
Version: 0.1.4
Summary: StitchLab agent core application
Author-email: StitchLab Team <evazuliya97@gmail.com>
License: MIT
Project-URL: Homepage, https://github.com/eva-zuliya/stitchlab-agentcore
Project-URL: Repository, https://github.com/eva-zuliya/stitchlab-agentcore
Project-URL: Issues, https://github.com/eva-zuliya/stitchlab-agentcore/issues
Keywords: agent,AWS AgentCore,ai
Classifier: Development Status :: 3 - Alpha
Classifier: Intended Audience :: Developers
Classifier: License :: OSI Approved :: MIT License
Classifier: Programming Language :: Python :: 3
Classifier: Programming Language :: Python :: 3.11
Classifier: Programming Language :: Python :: 3.12
Classifier: Programming Language :: Python :: 3.13
Requires-Python: <3.14,>=3.11
License-File: LICENSE
Requires-Dist: strands-agents==1.20.0
Requires-Dist: langfuse<3.0.0,>=2.0.0
Requires-Dist: bedrock-agentcore==1.1.1
Requires-Dist: fastapi==0.127.0
Requires-Dist: mcp==1.25.0
Requires-Dist: litellm==1.80.11
Requires-Dist: pydantic<3.0.0,>=1.10.0
Requires-Dist: python-dotenv>=1.0.0
Requires-Dist: opentelemetry-exporter-otlp-proto-http>=1.39.0
Provides-Extra: dev
Requires-Dist: pytest>=7.0.0; extra == "dev"
Requires-Dist: pytest-asyncio>=0.21.0; extra == "dev"
Requires-Dist: black>=23.0.0; extra == "dev"
Requires-Dist: ruff>=0.1.0; extra == "dev"
Dynamic: license-file
